{"id": "2524", "soundtrack": [{"features": {"analysis_url": "https://api.spotify.com/v1/audio-analysis/7swocJUCUWTCiRUAU9oerC", "tempo": 136.206, "valence": 0.306, "uri": "spotify:track:7swocJUCUWTCiRUAU9oerC", "time_signature": 4, "type": "audio_features", "mode": 1, "energy": 0.466, "acousticness": 0.134, "speechiness": 0.0317, "key": 4, "danceability": 0.636, "loudness": -15.534, "duration_ms": 175334, "id": "7swocJUCUWTCiRUAU9oerC", "track_href": "https://api.spotify.com/v1/tracks/7swocJUCUWTCiRUAU9oerC", "liveness": 0.156, "instrumentalness": 0.942}, "id": "7swocJUCUWTCiRUAU9oerC", "name": "Halloween Theme - Main Title"}, {"features": {"analysis_url": "https://api.spotify.com/v1/audio-analysis/0hz3MKhnEupwu03knyPJRC", "tempo": 81.463, "valence": 0.0447, "uri": "spotify:track:0hz3MKhnEupwu03knyPJRC", "time_signature": 4, "type": "audio_features", "mode": 0, "energy": 0.229, "acousticness": 0.965, "speechiness": 0.0502, "key": 11, "danceability": 0.417, "loudness": -18.656, "duration_ms": 55987, "id": "0hz3MKhnEupwu03knyPJRC", "track_href": "https://api.spotify.com/v1/tracks/0hz3MKhnEupwu03knyPJRC", "liveness": 0.0974, "instrumentalness": 0.889}, "id": "0hz3MKhnEupwu03knyPJRC", "name": "Something for Susan"}, {"features": "", "id": "", "missing": "Lisolette and Harlee", "name": ""}, {"features": {"analysis_url": "https://api.spotify.com/v1/audio-analysis/2AO3pFiVH3OFtksMVJOGCI", "tempo": 74.824, "valence": 0.191, "uri": "spotify:track:2AO3pFiVH3OFtksMVJOGCI", "time_signature": 4, "type": "audio_features", "mode": 0, "energy": 0.882, "acousticness": 0.00176, "speechiness": 0.0923, "key": 4, "danceability": 0.322, "loudness": -6.799, "duration_ms": 210946, "id": "2AO3pFiVH3OFtksMVJOGCI", "track_href": "https://api.spotify.com/v1/tracks/2AO3pFiVH3OFtksMVJOGCI", "liveness": 0.0859, "instrumentalness": 0.000393}, "id": "2AO3pFiVH3OFtksMVJOGCI", "name": "The Mirror Ignites the Sense"}, {"features": {"analysis_url": "https://api.spotify.com/v1/audio-analysis/33FQ9WlSEl4d348Jpchon2", "tempo": 75.98, "valence": 0.262, "uri": "spotify:track:33FQ9WlSEl4d348Jpchon2", "time_signature": 4, "type": "audio_features", "mode": 1, "energy": 0.258, "acousticness": 0.843, "speechiness": 0.0264, "key": 10, "danceability": 0.517, "loudness": -14.891, "duration_ms": 293827, "id": "33FQ9WlSEl4d348Jpchon2", "track_href": "https://api.spotify.com/v1/tracks/33FQ9WlSEl4d348Jpchon2", "liveness": 0.307, "instrumentalness": 0.00154}, "id": "33FQ9WlSEl4d348Jpchon2", "name": "One More Day"}, {"features": "", "id": "", "missing": "Harlee Dressing", "name": ""}, {"features": {"analysis_url": "https://api.spotify.com/v1/audio-analysis/1Aj0yDGPjvtjPAsIlz8I91", "tempo": 141.874, "valence": 0.147, "uri": "spotify:track:1Aj0yDGPjvtjPAsIlz8I91", "time_signature": 4, "type": "audio_features", "mode": 1, "energy": 0.456, "acousticness": 0.0499, "speechiness": 0.0347, "key": 0, "danceability": 0.171, "loudness": -9.559, "duration_ms": 451947, "id": "1Aj0yDGPjvtjPAsIlz8I91", "track_href": "https://api.spotify.com/v1/tracks/1Aj0yDGPjvtjPAsIlz8I91", "liveness": 0.991, "instrumentalness": 0.000294}, "id": "1Aj0yDGPjvtjPAsIlz8I91", "name": "Let There Be Light - Live"}, {"features": {"analysis_url": "https://api.spotify.com/v1/audio-analysis/2LOmJ4TEBaqeO8tf5vZD3g", "tempo": 72.941, "valence": 0.544, "uri": "spotify:track:2LOmJ4TEBaqeO8tf5vZD3g", "time_signature": 3, "type": "audio_features", "mode": 0, "energy": 0.0497, "acousticness": 0.996, "speechiness": 0.0382, "key": 3, "danceability": 0.305, "loudness": -19.479, "duration_ms": 278813, "id": "2LOmJ4TEBaqeO8tf5vZD3g", "track_href": "https://api.spotify.com/v1/tracks/2LOmJ4TEBaqeO8tf5vZD3g", "liveness": 0.129, "instrumentalness": 0.773}, "id": "2LOmJ4TEBaqeO8tf5vZD3g", "name": "Alone at Last"}, {"features": "", "id": "", "missing": "We May Never Love Like This Again  film version ", "name": ""}, {"features": {"analysis_url": "https://api.spotify.com/v1/audio-analysis/4lViRSNsjTp9Rl32RExasT", "tempo": 85.152, "valence": 0.434, "uri": "spotify:track:4lViRSNsjTp9Rl32RExasT", "time_signature": 4, "type": "audio_features", "mode": 1, "energy": 0.714, "acousticness": 0.457, "speechiness": 0.325, "key": 9, "danceability": 0.618, "loudness": -7.089, "duration_ms": 321893, "id": "4lViRSNsjTp9Rl32RExasT", "track_href": "https://api.spotify.com/v1/tracks/4lViRSNsjTp9Rl32RExasT", "liveness": 0.341, "instrumentalness": 0}, "id": "4lViRSNsjTp9Rl32RExasT", "name": "Victims of the Street"}, {"features": {"analysis_url": "https://api.spotify.com/v1/audio-analysis/1u1DjYp8LslTKFmZc6WfFK", "tempo": 91.308, "valence": 0.537, "uri": "spotify:track:1u1DjYp8LslTKFmZc6WfFK", "time_signature": 4, "type": "audio_features", "mode": 0, "energy": 0.472, "acousticness": 0.748, "speechiness": 0.106, "key": 11, "danceability": 0.549, "loudness": -5.893, "duration_ms": 211331, "id": "1u1DjYp8LslTKFmZc6WfFK", "track_href": "https://api.spotify.com/v1/tracks/1u1DjYp8LslTKFmZc6WfFK", "liveness": 0.0885, "instrumentalness": 0}, "id": "1u1DjYp8LslTKFmZc6WfFK", "name": "Buy A Cigarette"}, {"features": {"analysis_url": "https://api.spotify.com/v1/audio-analysis/5tyrRhTq8OxxbHvZJegSBg", "tempo": 115.02, "valence": 0.443, "uri": "spotify:track:5tyrRhTq8OxxbHvZJegSBg", "time_signature": 4, "type": "audio_features", "mode": 0, "energy": 0.711, "acousticness": 0.142, "speechiness": 0.0417, "key": 5, "danceability": 0.725, "loudness": -8.381, "duration_ms": 313500, "id": "5tyrRhTq8OxxbHvZJegSBg", "track_href": "https://api.spotify.com/v1/tracks/5tyrRhTq8OxxbHvZJegSBg", "liveness": 0.194, "instrumentalness": 0.00197}, "id": "5tyrRhTq8OxxbHvZJegSBg", "name": "Arguing Lovers"}, {"features": "", "id": "", "missing": "Doug s Fall   Piggy Back Ride", "name": ""}, {"features": "", "id": "", "missing": "Lisolette s Descent", "name": ""}, {"features": "", "id": "", "missing": "Down the Pipes   The Door Opens", "name": ""}, {"features": {"analysis_url": "https://api.spotify.com/v1/audio-analysis/3ahyFcydZjTa2oaeegCyxS", "tempo": 101.204, "valence": 0.346, "uri": "spotify:track:3ahyFcydZjTa2oaeegCyxS", "time_signature": 4, "type": "audio_features", "mode": 1, "energy": 0.797, "acousticness": 0.00177, "speechiness": 0.049, "key": 1, "danceability": 0.511, "loudness": -4.718, "duration_ms": 176385, "id": "3ahyFcydZjTa2oaeegCyxS", "track_href": "https://api.spotify.com/v1/tracks/3ahyFcydZjTa2oaeegCyxS", "liveness": 0.092, "instrumentalness": 1.22e-06}, "id": "3ahyFcydZjTa2oaeegCyxS", "name": "It's Cold Out Here"}, {"features": {"analysis_url": "https://api.spotify.com/v1/audio-analysis/5xBeuvjlfYDxjMNsiV9eiP", "tempo": 163.031, "valence": 0.557, "uri": "spotify:track:5xBeuvjlfYDxjMNsiV9eiP", "time_signature": 4, "type": "audio_features", "mode": 1, "energy": 0.916, "acousticness": 0.0157, "speechiness": 0.0536, "key": 11, "danceability": 0.513, "loudness": -4.999, "duration_ms": 220839, "id": "5xBeuvjlfYDxjMNsiV9eiP", "track_href": "https://api.spotify.com/v1/tracks/5xBeuvjlfYDxjMNsiV9eiP", "liveness": 0.142, "instrumentalness": 0}, "id": "5xBeuvjlfYDxjMNsiV9eiP", "name": "Sunrise Goodbyes"}, {"features": {"analysis_url": "https://api.spotify.com/v1/audio-analysis/4PgFniaCRAhxDl10y3ySru", "tempo": 121.09, "valence": 0.0355, "uri": "spotify:track:4PgFniaCRAhxDl10y3ySru", "time_signature": 4, "type": "audio_features", "mode": 1, "energy": 0.0946, "acousticness": 0.772, "speechiness": 0.0469, "key": 0, "danceability": 0.173, "loudness": -17.229, "duration_ms": 125720, "id": "4PgFniaCRAhxDl10y3ySru", "track_href": "https://api.spotify.com/v1/tracks/4PgFniaCRAhxDl10y3ySru", "liveness": 0.0466, "instrumentalness": 0.946}, "id": "4PgFniaCRAhxDl10y3ySru", "name": "Helicopter Rescue"}, {"features": "", "id": "", "missing": "Passing the Word", "name": ""}, {"features": {"analysis_url": "https://api.spotify.com/v1/audio-analysis/1bIA9SlbPgwt3unJlGqji9", "tempo": 110.177, "valence": 0.0369, "uri": "spotify:track:1bIA9SlbPgwt3unJlGqji9", "time_signature": 4, "type": "audio_features", "mode": 1, "energy": 0.118, "acousticness": 0.847, "speechiness": 0.0362, "key": 5, "danceability": 0.21, "loudness": -17.921, "duration_ms": 663800, "id": "1bIA9SlbPgwt3unJlGqji9", "track_href": "https://api.spotify.com/v1/tracks/1bIA9SlbPgwt3unJlGqji9", "liveness": 0.11, "instrumentalness": 0.651}, "id": "1bIA9SlbPgwt3unJlGqji9", "name": "The Towering Inferno: Planting The Charges And Finale"}, {"features": {"analysis_url": "https://api.spotify.com/v1/audio-analysis/0DanGj9TtgZIjJnHdTbW9v", "tempo": 92.131, "valence": 0.19, "uri": "spotify:track:0DanGj9TtgZIjJnHdTbW9v", "time_signature": 4, "type": "audio_features", "mode": 0, "energy": 0.863, "acousticness": 0.00655, "speechiness": 0.0473, "key": 7, "danceability": 0.42, "loudness": -3.135, "duration_ms": 205200, "id": "0DanGj9TtgZIjJnHdTbW9v", "track_href": "https://api.spotify.com/v1/tracks/0DanGj9TtgZIjJnHdTbW9v", "liveness": 0.147, "instrumentalness": 1.39e-05}, "id": "0DanGj9TtgZIjJnHdTbW9v", "name": "Finale"}, {"features": "", "id": "", "missing": "An Architect s Dream", "name": ""}, {"features": "", "id": "", "missing": "We May Never Love Like This Again  album version ", "name": ""}, {"features": {"analysis_url": "https://api.spotify.com/v1/audio-analysis/24FJc7FGTJJbOCyfGzeRl9", "tempo": 123.017, "valence": 0.755, "uri": "spotify:track:24FJc7FGTJJbOCyfGzeRl9", "time_signature": 4, "type": "audio_features", "mode": 1, "energy": 0.384, "acousticness": 0.495, "speechiness": 0.0449, "key": 7, "danceability": 0.746, "loudness": -10.383, "duration_ms": 444918, "id": "24FJc7FGTJJbOCyfGzeRl9", "track_href": "https://api.spotify.com/v1/tracks/24FJc7FGTJJbOCyfGzeRl9", "liveness": 0.0932, "instrumentalness": 0.908}, "id": "24FJc7FGTJJbOCyfGzeRl9", "name": "The Morning After (Broken Beat Session Mix) [Instrumental]"}, {"features": "", "id": "", "missing": "Susan and Doug  album track ", "name": ""}, {"features": "", "id": "", "missing": "Departmental Pride and the Cat  damaged ", "name": ""}, {"features": "", "id": "", "missing": "Helicopter Explosion  damaged ", "name": ""}, {"features": {"analysis_url": "https://api.spotify.com/v1/audio-analysis/4WBulhQHvKfyllAIRBBB9g", "tempo": 82.856, "valence": null, "uri": "spotify:track:4WBulhQHvKfyllAIRBBB9g", "time_signature": 4, "type": "audio_features", "mode": 1, "energy": 0.0026, "acousticness": 0.984, "speechiness": 0.0523, "key": 4, "danceability": 0.395, "loudness": -38.889, "duration_ms": 30000, "id": "4WBulhQHvKfyllAIRBBB9g", "track_href": "https://api.spotify.com/v1/tracks/4WBulhQHvKfyllAIRBBB9g", "liveness": 0.0913, "instrumentalness": 0.981}, "id": "4WBulhQHvKfyllAIRBBB9g", "name": "Waking Up"}], "name": "Towering Inferno, The (1974)"}