{"id": "3152", "soundtrack": [{"features": {"analysis_url": "https://api.spotify.com/v1/audio-analysis/1nz7qrpaifFdBUp22qde4O", "tempo": 66.305, "valence": 0.307, "uri": "spotify:track:1nz7qrpaifFdBUp22qde4O", "time_signature": 3, "type": "audio_features", "mode": 1, "energy": 0.141, "acousticness": 0.968, "speechiness": 0.039, "key": 7, "danceability": 0.37, "loudness": -14.082, "duration_ms": 159520, "id": "1nz7qrpaifFdBUp22qde4O", "track_href": "https://api.spotify.com/v1/tracks/1nz7qrpaifFdBUp22qde4O", "liveness": 0.338, "instrumentalness": 1.59e-06}, "id": "1nz7qrpaifFdBUp22qde4O", "name": "Cold Cold Heart"}, {"features": {"analysis_url": "https://api.spotify.com/v1/audio-analysis/6yjTy2DDQLmJgrXXx0eaUU", "tempo": 200.883, "valence": 0.832, "uri": "spotify:track:6yjTy2DDQLmJgrXXx0eaUU", "time_signature": 4, "type": "audio_features", "mode": 1, "energy": 0.328, "acousticness": 0.875, "speechiness": 0.0947, "key": 2, "danceability": 0.51, "loudness": -12.813, "duration_ms": 135427, "id": "6yjTy2DDQLmJgrXXx0eaUU", "track_href": "https://api.spotify.com/v1/tracks/6yjTy2DDQLmJgrXXx0eaUU", "liveness": 0.212, "instrumentalness": 0}, "id": "6yjTy2DDQLmJgrXXx0eaUU", "name": "Give Me More, More, More (Of Your Kisses)"}, {"features": {"analysis_url": "https://api.spotify.com/v1/audio-analysis/12FenJTid0ehEheP8Cs8Ff", "tempo": 114.317, "valence": 0.35, "uri": "spotify:track:12FenJTid0ehEheP8Cs8Ff", "time_signature": 4, "type": "audio_features", "mode": 1, "energy": 0.221, "acousticness": 0.856, "speechiness": 0.0349, "key": 5, "danceability": 0.39, "loudness": -14.658, "duration_ms": 174400, "id": "12FenJTid0ehEheP8Cs8Ff", "track_href": "https://api.spotify.com/v1/tracks/12FenJTid0ehEheP8Cs8Ff", "liveness": 0.369, "instrumentalness": 0}, "id": "12FenJTid0ehEheP8Cs8Ff", "name": "Wish You Were Here"}, {"features": {"analysis_url": "https://api.spotify.com/v1/audio-analysis/0h45YvcNfRRpf5D34vVgOr", "tempo": 133.907, "valence": 0.786, "uri": "spotify:track:0h45YvcNfRRpf5D34vVgOr", "time_signature": 4, "type": "audio_features", "mode": 1, "energy": 0.175, "acousticness": 0.732, "speechiness": 0.138, "key": 7, "danceability": 0.756, "loudness": -15.094, "duration_ms": 180560, "id": "0h45YvcNfRRpf5D34vVgOr", "track_href": "https://api.spotify.com/v1/tracks/0h45YvcNfRRpf5D34vVgOr", "liveness": 0.0737, "instrumentalness": 2.47e-06}, "id": "0h45YvcNfRRpf5D34vVgOr", "name": "Slow Poke - Single Version"}, {"features": {"analysis_url": "https://api.spotify.com/v1/audio-analysis/1icxduZe57KTaogd6BGfxV", "tempo": 66.134, "valence": 0.0828, "uri": "spotify:track:1icxduZe57KTaogd6BGfxV", "time_signature": 4, "type": "audio_features", "mode": 0, "energy": 0.283, "acousticness": 0.886, "speechiness": 0.0318, "key": 11, "danceability": 0.108, "loudness": -13.472, "duration_ms": 272573, "id": "1icxduZe57KTaogd6BGfxV", "track_href": "https://api.spotify.com/v1/tracks/1icxduZe57KTaogd6BGfxV", "liveness": 0.0779, "instrumentalness": 0.000444}, "id": "1icxduZe57KTaogd6BGfxV", "name": "Blue Velvet"}, {"features": "", "id": "", "missing": "Rose  Rose  I Love You  Frankie Lane ", "name": ""}, {"features": {"analysis_url": "https://api.spotify.com/v1/audio-analysis/4ifZT2TGYtOUIV7IW9NFBB", "tempo": 73.168, "valence": 0.33, "uri": "spotify:track:4ifZT2TGYtOUIV7IW9NFBB", "time_signature": 4, "type": "audio_features", "mode": 1, "energy": 0.203, "acousticness": 0.977, "speechiness": 0.031, "key": 10, "danceability": 0.392, "loudness": -13.916, "duration_ms": 185333, "id": "4ifZT2TGYtOUIV7IW9NFBB", "track_href": "https://api.spotify.com/v1/tracks/4ifZT2TGYtOUIV7IW9NFBB", "liveness": 0.176, "instrumentalness": 0}, "id": "4ifZT2TGYtOUIV7IW9NFBB", "name": "You Belong To Me"}, {"features": {"analysis_url": "https://api.spotify.com/v1/audio-analysis/2OxaRLfB2mcu20ale73wSV", "tempo": 113.276, "valence": 0.551, "uri": "spotify:track:2OxaRLfB2mcu20ale73wSV", "time_signature": 4, "type": "audio_features", "mode": 1, "energy": 0.412, "acousticness": 0.621, "speechiness": 0.0273, "key": 8, "danceability": 0.543, "loudness": -9.436, "duration_ms": 148427, "id": "2OxaRLfB2mcu20ale73wSV", "track_href": "https://api.spotify.com/v1/tracks/2OxaRLfB2mcu20ale73wSV", "liveness": 0.238, "instrumentalness": 0.000256}, "id": "2OxaRLfB2mcu20ale73wSV", "name": "(Now and Then, There's) A Fool Such As I - Single Version"}, {"features": {"analysis_url": "https://api.spotify.com/v1/audio-analysis/5n07Qq7XrGE3w9OAnd871P", "tempo": 175.601, "valence": 0.227, "uri": "spotify:track:5n07Qq7XrGE3w9OAnd871P", "time_signature": 3, "type": "audio_features", "mode": 0, "energy": 0.0995, "acousticness": 0.97, "speechiness": 0.0362, "key": 4, "danceability": 0.336, "loudness": -16.101, "duration_ms": 177533, "id": "5n07Qq7XrGE3w9OAnd871P", "track_href": "https://api.spotify.com/v1/tracks/5n07Qq7XrGE3w9OAnd871P", "liveness": 0.0875, "instrumentalness": 0}, "id": "5n07Qq7XrGE3w9OAnd871P", "name": "Please, Mr. Sun"}, {"features": {"analysis_url": "https://api.spotify.com/v1/audio-analysis/4DCqxiuqN5JbTWDh9tNEd1", "tempo": 99.368, "valence": 0.116, "uri": "spotify:track:4DCqxiuqN5JbTWDh9tNEd1", "time_signature": 3, "type": "audio_features", "mode": 1, "energy": 0.253, "acousticness": 0.962, "speechiness": 0.0362, "key": 2, "danceability": 0.277, "loudness": -13.156, "duration_ms": 196400, "id": "4DCqxiuqN5JbTWDh9tNEd1", "track_href": "https://api.spotify.com/v1/tracks/4DCqxiuqN5JbTWDh9tNEd1", "liveness": 0.089, "instrumentalness": 0.0204}, "id": "4DCqxiuqN5JbTWDh9tNEd1", "name": "Solitaire - 2011 Remaster"}], "name": "Last Picture Show, The (1971)"}