{"id": "3451", "soundtrack": [{"features": "", "id": "", "missing": "Guess Who s Coming To Dinner  Theme ", "name": ""}, {"features": "", "id": "", "missing": "Two s A Majority", "name": ""}, {"features": {"analysis_url": "https://api.spotify.com/v1/audio-analysis/6F2czMu3r2orV7CR3uMfqE", "tempo": 114.375, "valence": 0.614, "uri": "spotify:track:6F2czMu3r2orV7CR3uMfqE", "time_signature": 4, "type": "audio_features", "mode": 1, "energy": 0.517, "acousticness": 0.638, "speechiness": 0.0363, "key": 5, "danceability": 0.554, "loudness": -7.519, "duration_ms": 211333, "id": "6F2czMu3r2orV7CR3uMfqE", "track_href": "https://api.spotify.com/v1/tracks/6F2czMu3r2orV7CR3uMfqE", "liveness": 0.109, "instrumentalness": 1.98e-05}, "id": "6F2czMu3r2orV7CR3uMfqE", "name": "Dear Old Dad"}, {"features": {"analysis_url": "https://api.spotify.com/v1/audio-analysis/7zhxXSGNMVuWMOsFLq1r9h", "tempo": 121.143, "valence": 0.413, "uri": "spotify:track:7zhxXSGNMVuWMOsFLq1r9h", "time_signature": 4, "type": "audio_features", "mode": 1, "energy": 0.171, "acousticness": 0.901, "speechiness": 0.0375, "key": 3, "danceability": 0.482, "loudness": -13.592, "duration_ms": 197080, "id": "7zhxXSGNMVuWMOsFLq1r9h", "track_href": "https://api.spotify.com/v1/tracks/7zhxXSGNMVuWMOsFLq1r9h", "liveness": 0.105, "instrumentalness": 0}, "id": "7zhxXSGNMVuWMOsFLq1r9h", "name": "Skyway Drive-In"}, {"features": {"analysis_url": "https://api.spotify.com/v1/audio-analysis/0I7VsQS5ehomS5TIi55VMI", "tempo": 175.01, "valence": 0.841, "uri": "spotify:track:0I7VsQS5ehomS5TIi55VMI", "time_signature": 4, "type": "audio_features", "mode": 1, "energy": 0.585, "acousticness": 0.0093, "speechiness": 0.0767, "key": 0, "danceability": 0.814, "loudness": -5.456, "duration_ms": 168800, "id": "0I7VsQS5ehomS5TIi55VMI", "track_href": "https://api.spotify.com/v1/tracks/0I7VsQS5ehomS5TIi55VMI", "liveness": 0.159, "instrumentalness": 0.0018}, "id": "0I7VsQS5ehomS5TIi55VMI", "name": "Happy With Me"}, {"features": "", "id": "", "missing": "Guess Who s Coming To Dinner  Reprise ", "name": ""}, {"features": "", "id": "", "missing": "The Glory Of Love  written by Billy Hill ", "name": ""}, {"features": "", "id": "", "missing": "Guess Who s Coming To Dinner   nd Reprise ", "name": ""}, {"features": "", "id": "", "missing": "Groovy Delivery Boy", "name": ""}, {"features": "", "id": "", "missing": "Sentimental Suitcase", "name": ""}, {"features": {"analysis_url": "https://api.spotify.com/v1/audio-analysis/61sXY8wcOxRrEhezeE3loA", "tempo": 100.939, "valence": 0.034, "uri": "spotify:track:61sXY8wcOxRrEhezeE3loA", "time_signature": 3, "type": "audio_features", "mode": 1, "energy": 0.159, "acousticness": 0.965, "speechiness": 0.038, "key": 0, "danceability": 0.254, "loudness": -18.24, "duration_ms": 53403, "id": "61sXY8wcOxRrEhezeE3loA", "track_href": "https://api.spotify.com/v1/tracks/61sXY8wcOxRrEhezeE3loA", "liveness": 0.109, "instrumentalness": 0.992}, "id": "61sXY8wcOxRrEhezeE3loA", "name": "Power and Glory"}], "name": "Guess Who's Coming to Dinner (1967)"}