{"id": "3639", "soundtrack": [{"features": "", "id": "", "missing": "Main Title    The Man With The Golden Gun    Lulu", "name": ""}, {"features": "", "id": "", "missing": "Scaramanga s Fun House", "name": ""}, {"features": {"analysis_url": "https://api.spotify.com/v1/audio-analysis/493KB1lBdWE1dr7NiO6amM", "tempo": 80.042, "valence": 0.0545, "uri": "spotify:track:493KB1lBdWE1dr7NiO6amM", "time_signature": 4, "type": "audio_features", "mode": 1, "energy": 0.0733, "acousticness": 0.768, "speechiness": 0.0377, "key": 4, "danceability": 0.178, "loudness": -19.003, "duration_ms": 277293, "id": "493KB1lBdWE1dr7NiO6amM", "track_href": "https://api.spotify.com/v1/tracks/493KB1lBdWE1dr7NiO6amM", "liveness": 0.167, "instrumentalness": 0.712}, "id": "493KB1lBdWE1dr7NiO6amM", "name": "The Man With The Golden Gun (Chew Me In Grisly Land/Return To Scaramanga's Fun H"}, {"features": "", "id": "", "missing": "The Man With The Golden Gun  Jazz Instrumental ", "name": ""}, {"features": {"analysis_url": "https://api.spotify.com/v1/audio-analysis/5487tDNb3Bon5ClkEQg24W", "tempo": 116.745, "valence": 0.108, "uri": "spotify:track:5487tDNb3Bon5ClkEQg24W", "time_signature": 4, "type": "audio_features", "mode": 0, "energy": 0.0592, "acousticness": 0.974, "speechiness": 0.0408, "key": 4, "danceability": 0.356, "loudness": -17.268, "duration_ms": 165512, "id": "5487tDNb3Bon5ClkEQg24W", "track_href": "https://api.spotify.com/v1/tracks/5487tDNb3Bon5ClkEQg24W", "liveness": 0.119, "instrumentalness": 0.305}, "id": "5487tDNb3Bon5ClkEQg24W", "name": "Getting The Bullet"}, {"features": {"analysis_url": "https://api.spotify.com/v1/audio-analysis/5dTHtzHFPyi8TlTtzoz1J9", "tempo": 125.921, "valence": 0.0915, "uri": "spotify:track:5dTHtzHFPyi8TlTtzoz1J9", "time_signature": 4, "type": "audio_features", "mode": 1, "energy": 0.96, "acousticness": 0.0142, "speechiness": 0.104, "key": 4, "danceability": 0.356, "loudness": -3.487, "duration_ms": 204733, "id": "5dTHtzHFPyi8TlTtzoz1J9", "track_href": "https://api.spotify.com/v1/tracks/5dTHtzHFPyi8TlTtzoz1J9", "liveness": 0.209, "instrumentalness": 0}, "id": "5dTHtzHFPyi8TlTtzoz1J9", "name": "Helena (So Long & Goodnight)"}, {"features": "", "id": "", "missing": "Let s Go Get  Em", "name": ""}, {"features": {"analysis_url": "https://api.spotify.com/v1/audio-analysis/51vqu7mlPdkTSsfcwtbYHK", "tempo": 94.985, "valence": 0.555, "uri": "spotify:track:51vqu7mlPdkTSsfcwtbYHK", "time_signature": 4, "type": "audio_features", "mode": 0, "energy": 0.237, "acousticness": 0.336, "speechiness": 0.0616, "key": 7, "danceability": 0.861, "loudness": -18.044, "duration_ms": 142453, "id": "51vqu7mlPdkTSsfcwtbYHK", "track_href": "https://api.spotify.com/v1/tracks/51vqu7mlPdkTSsfcwtbYHK", "liveness": 0.121, "instrumentalness": 0.8}, "id": "51vqu7mlPdkTSsfcwtbYHK", "name": "It?S Ok"}, {"features": {"analysis_url": "https://api.spotify.com/v1/audio-analysis/1VwPMVYbZzfNh74kM4ikbL", "tempo": 113.063, "valence": 0.0363, "uri": "spotify:track:1VwPMVYbZzfNh74kM4ikbL", "time_signature": 4, "type": "audio_features", "mode": 0, "energy": 0.783, "acousticness": 0.473, "speechiness": 0.0715, "key": 11, "danceability": 0.473, "loudness": -15.789, "duration_ms": 128693, "id": "1VwPMVYbZzfNh74kM4ikbL", "track_href": "https://api.spotify.com/v1/tracks/1VwPMVYbZzfNh74kM4ikbL", "liveness": 0.116, "instrumentalness": 0.893}, "id": "1VwPMVYbZzfNh74kM4ikbL", "name": "Casino Fight"}, {"features": "", "id": "", "missing": "In Search of Scaramanga s Island", "name": ""}, {"features": "", "id": "", "missing": "Return to Scaramanga s Fun House", "name": ""}, {"features": "", "id": "", "missing": "End Title    The Man With The Golden Gun    Lulu", "name": ""}], "name": "Man with the Golden Gun, The (1974)"}