{"id": "3917", "soundtrack": [{"features": {"analysis_url": "https://api.spotify.com/v1/audio-analysis/1S5ScNIHpNZWOOgXfgF6xl", "tempo": 119.965, "valence": 0.213, "uri": "spotify:track:1S5ScNIHpNZWOOgXfgF6xl", "time_signature": 4, "type": "audio_features", "mode": 1, "energy": 0.962, "acousticness": 0.000363, "speechiness": 0.0539, "key": 1, "danceability": 0.601, "loudness": -3.235, "duration_ms": 175493, "id": "1S5ScNIHpNZWOOgXfgF6xl", "track_href": "https://api.spotify.com/v1/tracks/1S5ScNIHpNZWOOgXfgF6xl", "liveness": 0.204, "instrumentalness": 0.0133}, "id": "1S5ScNIHpNZWOOgXfgF6xl", "name": "Hellraiser"}, {"features": {"analysis_url": "https://api.spotify.com/v1/audio-analysis/7GaiL46MFjCh4LfEDeM8HY", "tempo": 75.04, "valence": 0.215, "uri": "spotify:track:7GaiL46MFjCh4LfEDeM8HY", "time_signature": 4, "type": "audio_features", "mode": 1, "energy": 0.355, "acousticness": 0.284, "speechiness": 0.0287, "key": 5, "danceability": 0.513, "loudness": -9.997, "duration_ms": 289800, "id": "7GaiL46MFjCh4LfEDeM8HY", "track_href": "https://api.spotify.com/v1/tracks/7GaiL46MFjCh4LfEDeM8HY", "liveness": 0.108, "instrumentalness": 0}, "id": "7GaiL46MFjCh4LfEDeM8HY", "name": "Resurrection Fern"}, {"features": {"analysis_url": "https://api.spotify.com/v1/audio-analysis/6ygo6YccVWJ3hDlz5a68CU", "tempo": 165.006, "valence": 0.668, "uri": "spotify:track:6ygo6YccVWJ3hDlz5a68CU", "time_signature": 4, "type": "audio_features", "mode": 1, "energy": 0.949, "acousticness": 0.000451, "speechiness": 0.0591, "key": 0, "danceability": 0.453, "loudness": -3.759, "duration_ms": 169942, "id": "6ygo6YccVWJ3hDlz5a68CU", "track_href": "https://api.spotify.com/v1/tracks/6ygo6YccVWJ3hDlz5a68CU", "liveness": 0.38, "instrumentalness": 0}, "id": "6ygo6YccVWJ3hDlz5a68CU", "name": "Hellbound"}, {"features": "", "id": "", "missing": "The Lament Comfiguration", "name": ""}, {"features": {"analysis_url": "https://api.spotify.com/v1/audio-analysis/4mSp2FCzwGUN58aurJawQq", "tempo": 87.814, "valence": 0.662, "uri": "spotify:track:4mSp2FCzwGUN58aurJawQq", "time_signature": 4, "type": "audio_features", "mode": 1, "energy": 0.654, "acousticness": 0.0161, "speechiness": 0.245, "key": 1, "danceability": 0.728, "loudness": -7.044, "duration_ms": 337053, "id": "4mSp2FCzwGUN58aurJawQq", "track_href": "https://api.spotify.com/v1/tracks/4mSp2FCzwGUN58aurJawQq", "liveness": 0.341, "instrumentalness": 0}, "id": "4mSp2FCzwGUN58aurJawQq", "name": "Boyz-N-The-Hood"}, {"features": {"analysis_url": "https://api.spotify.com/v1/audio-analysis/2AoXzmimyz5fzGroJzVLSC", "tempo": 93.944, "valence": 0.85, "uri": "spotify:track:2AoXzmimyz5fzGroJzVLSC", "time_signature": 4, "type": "audio_features", "mode": 1, "energy": 0.925, "acousticness": 0.0575, "speechiness": 0.0479, "key": 9, "danceability": 0.59, "loudness": -5.622, "duration_ms": 237451, "id": "2AoXzmimyz5fzGroJzVLSC", "track_href": "https://api.spotify.com/v1/tracks/2AoXzmimyz5fzGroJzVLSC", "liveness": 0.364, "instrumentalness": 0}, "id": "2AoXzmimyz5fzGroJzVLSC", "name": "A Quick Death in Texas"}, {"features": "", "id": "", "missing": "Seduction And Pursuit", "name": ""}, {"features": {"analysis_url": "https://api.spotify.com/v1/audio-analysis/1xkLLbpo3y4KNy64EFVB9C", "tempo": 115.884, "valence": 0.507, "uri": "spotify:track:1xkLLbpo3y4KNy64EFVB9C", "time_signature": 4, "type": "audio_features", "mode": 1, "energy": 0.633, "acousticness": 0.799, "speechiness": 0.0287, "key": 0, "danceability": 0.603, "loudness": -5.832, "duration_ms": 172040, "id": "1xkLLbpo3y4KNy64EFVB9C", "track_href": "https://api.spotify.com/v1/tracks/1xkLLbpo3y4KNy64EFVB9C", "liveness": 0.115, "instrumentalness": 0}, "id": "1xkLLbpo3y4KNy64EFVB9C", "name": "Stop! In The Name Of Love"}, {"features": {"analysis_url": "https://api.spotify.com/v1/audio-analysis/2eriGmvgrxYhTK7yTgXr8M", "tempo": 119.037, "valence": 0.0357, "uri": "spotify:track:2eriGmvgrxYhTK7yTgXr8M", "time_signature": 4, "type": "audio_features", "mode": 1, "energy": 0.988, "acousticness": 2.71e-05, "speechiness": 0.429, "key": 11, "danceability": 0.212, "loudness": -4.861, "duration_ms": 328467, "id": "2eriGmvgrxYhTK7yTgXr8M", "track_href": "https://api.spotify.com/v1/tracks/2eriGmvgrxYhTK7yTgXr8M", "liveness": 0.371, "instrumentalness": 0.889}, "id": "2eriGmvgrxYhTK7yTgXr8M", "name": "Cenobites"}, {"features": "", "id": "", "missing": "The Rat Race Slice Quartet", "name": ""}, {"features": {"analysis_url": "https://api.spotify.com/v1/audio-analysis/2XKnkbm2U2EXN6ljt1vfmz", "tempo": 120.643, "valence": 0.209, "uri": "spotify:track:2XKnkbm2U2EXN6ljt1vfmz", "time_signature": 4, "type": "audio_features", "mode": 1, "energy": 0.686, "acousticness": 0.0475, "speechiness": 0.0334, "key": 7, "danceability": 0.59, "loudness": -5.559, "duration_ms": 219802, "id": "2XKnkbm2U2EXN6ljt1vfmz", "track_href": "https://api.spotify.com/v1/tracks/2XKnkbm2U2EXN6ljt1vfmz", "liveness": 0.209, "instrumentalness": 0}, "id": "2XKnkbm2U2EXN6ljt1vfmz", "name": "Resurrection"}, {"features": {"analysis_url": "https://api.spotify.com/v1/audio-analysis/4PPwkLq2ld1k09Bl5NkyZB", "tempo": 162.461, "valence": 0.717, "uri": "spotify:track:4PPwkLq2ld1k09Bl5NkyZB", "time_signature": 4, "type": "audio_features", "mode": 1, "energy": 0.646, "acousticness": 0.0322, "speechiness": 0.0411, "key": 0, "danceability": 0.38, "loudness": -11.13, "duration_ms": 169600, "id": "4PPwkLq2ld1k09Bl5NkyZB", "track_href": "https://api.spotify.com/v1/tracks/4PPwkLq2ld1k09Bl5NkyZB", "liveness": 0.0872, "instrumentalness": 0.0282}, "id": "4PPwkLq2ld1k09Bl5NkyZB", "name": "Uncle Remus"}, {"features": "", "id": "", "missing": "Brought On By Night", "name": ""}, {"features": {"analysis_url": "https://api.spotify.com/v1/audio-analysis/6RSU0jdE5fX5iPdLgKNAFk", "tempo": 84.97, "valence": 0.703, "uri": "spotify:track:6RSU0jdE5fX5iPdLgKNAFk", "time_signature": 4, "type": "audio_features", "mode": 1, "energy": 0.524, "acousticness": 0.27, "speechiness": 0.0338, "key": 7, "danceability": 0.758, "loudness": -7.386, "duration_ms": 183446, "id": "6RSU0jdE5fX5iPdLgKNAFk", "track_href": "https://api.spotify.com/v1/tracks/6RSU0jdE5fX5iPdLgKNAFk", "liveness": 0.314, "instrumentalness": 0}, "id": "6RSU0jdE5fX5iPdLgKNAFk", "name": "Another Sunrise"}], "name": "Hellraiser (1987)"}